nlcomputer/__init__.py
nlcomputer/core/__init__.py
nlcomputer/core/message.py
nlcomputer-0.0.1.dist-info/WHEEL
nlcomputer-0.0.1.dist-info/METADATA
nlcomputer-0.0.1.dist-info/RECORD
