Metadata-Version: 2.1
Name: nlcomputer
Version: 0.0.1
Summary: Natural Language Computer (see https://github.com/fixie-ai/nlc)
Author: Fixie.ai Team
Author-email: hello@fixie.ai
Requires-Python: >=3.8,<4.0
Classifier: Programming Language :: Python :: 3
Classifier: Programming Language :: Python :: 3.8
Classifier: Programming Language :: Python :: 3.9
Classifier: Programming Language :: Python :: 3.10
